compas_invocations2/__init__.py
compas_invocations2/build.py
compas_invocations2/console.py
compas_invocations2/docs.py
compas_invocations2/grasshopper.py
compas_invocations2/style.py
compas_invocations2/tests.py
compas_invocations2-0.6.0.dist-info/licenses/LICENSE
compas_invocations2-0.6.0.dist-info/METADATA
compas_invocations2-0.6.0.dist-info/WHEEL
compas_invocations2-0.6.0.dist-info/top_level.txt
compas_invocations2-0.6.0.dist-info/RECORD
