Metadata-Version: 2.4
Name: compas_invocations2
Version: 0.6.0
Summary: A collection of reusable pyinvoke tasks.
Author-email: Li Chen <li.chen@arch.ethz.ch>
License: MIT License
Project-URL: Homepage, https://compas-dev.github.io/compas_invocations2
Project-URL: Documentation, https://compas-dev.github.io/compas_invocations2
Project-URL: Repository, https://github.com/compas-dev/compas_invocations2.git
Project-URL: Changelog, https://github.com/compas-dev/compas_invocations2/blob/main/CHANGELOG.md
Classifier: Development Status :: 4 - Beta
Classifier: Topic :: Scientific/Engineering
Classifier: Programming Language :: Python
Classifier: Programming Language :: Python :: 3
Classifier: Programming Language :: Python :: 3.9
Classifier: Programming Language :: Python :: 3.10
Classifier: Programming Language :: Python :: 3.11
Requires-Python: >=3.9
License-File: LICENSE
Provides-Extra: dev
Requires-Dist: attrs>=17.4; extra == "dev"
Requires-Dist: black>=22.12.0; extra == "dev"
Requires-Dist: bump-my-version; extra == "dev"
Requires-Dist: compas_notebook; extra == "dev"
Requires-Dist: invoke>=0.14; extra == "dev"
Requires-Dist: ruff; extra == "dev"
Requires-Dist: sphinx_compas2_theme; extra == "dev"
Requires-Dist: twine; extra == "dev"
Requires-Dist: wheel; extra == "dev"
Requires-Dist: tomlkit; extra == "dev"
Dynamic: license-file
